README.rst
setup.py
tlclient/__init__.py
tlclient.egg-info/PKG-INFO
tlclient.egg-info/SOURCES.txt
tlclient.egg-info/dependency_links.txt
tlclient.egg-info/requires.txt
tlclient.egg-info/top_level.txt
tlclient/linker/__init__.py
tlclient/linker/_version.py
tlclient/linker/batch.py
tlclient/linker/constant.py
tlclient/linker/event.py
tlclient/linker/exception.py
tlclient/linker/fist.py
tlclient/linker/frame.py
tlclient/linker/logger.py
tlclient/linker/message_comm.py
tlclient/linker/rsa_encrypter.py
tlclient/linker/structs.py
tlclient/linker/timer.py
tlclient/linker/utility.py
tlclient/linker/pb_msg/__init__.py
tlclient/linker/pb_msg/comm_pb2.py
tlclient/linker/pb_msg/frame_pb2.py
tlclient/linker/pb_msg/helper.py
tlclient/trader/__init__.py
tlclient/trader/__main__.py
tlclient/trader/_version.py
tlclient/trader/analyzer.py
tlclient/trader/checker.py
tlclient/trader/client.py
tlclient/trader/combo_client.py
tlclient/trader/combo_client_2.py
tlclient/trader/config.py
tlclient/trader/constant.py
tlclient/trader/gateway.py
tlclient/trader/gun.py
tlclient/trader/gun_helpers.py
tlclient/trader/invoke_helpers.py
tlclient/trader/invoker.py
tlclient/trader/market_gateway.py
tlclient/trader/message_common.py
tlclient/trader/message_market.py
tlclient/trader/message_trade.py
tlclient/trader/mongo_connector.py
tlclient/trader/next_oms.py
tlclient/trader/notification.py
tlclient/trader/oms.py
tlclient/trader/param_server.py
tlclient/trader/recorder.py
tlclient/trader/risk_test_client.py
tlclient/trader/timer_helper.py
tlclient/trader/trade_gateway.py
tlclient/trader/tunnel_client.py
tlclient/trader/utils.py
tlclient/trader/wechat_bot.py
tlclient/trader/data_manager/__init__.py
tlclient/trader/data_manager/_version.py
tlclient/trader/data_manager/dm_client.py
tlclient/trader/data_manager/dm_error.py
tlclient/trader/database/__init__.py
tlclient/trader/database/connector.py
tlclient/trader/database/migrate_scripts.py
tlclient/trader/database/models.py
tlclient/trader/database/oms_models.py
tlclient/trader/database/sqlite_models.py
tlclient/trader/helpers/__init__.py
tlclient/trader/helpers/account_helper.py
