Metadata-Version: 1.2
Name: tlclient
Version: 0.6.65
Summary: strategy side SDK for traders.link
Home-page: http://docs.puyuan.tech
Author: puyuan.tech
Author-email: info@puyuan.tech
Maintainer: puyuan_staff
Maintainer-email: github@puyuan.tech
License: MIT License
Platform: all
Classifier: Development Status :: 4 - Beta
Classifier: Operating System :: OS Independent
Classifier: Intended Audience :: Developers
Classifier: License :: OSI Approved :: MIT License
Classifier: Programming Language :: Python
Classifier: Programming Language :: Python :: Implementation
Classifier: Programming Language :: Python :: 2
Classifier: Programming Language :: Python :: 2.7
Classifier: Programming Language :: Python :: 3.7
Classifier: Topic :: Software Development :: Libraries
